aprsd_weewx_plugin/__init__.py
aprsd_weewx_plugin/conf.py
aprsd_weewx_plugin/weewx.py
aprsd_weewx_plugin/conf/__init__.py
aprsd_weewx_plugin/conf/opts.py
aprsd_weewx_plugin/conf/weewx.py
aprsd_weewx_plugin-0.3.2.dist-info/LICENSE
aprsd_weewx_plugin-0.3.2.dist-info/METADATA
aprsd_weewx_plugin-0.3.2.dist-info/WHEEL
aprsd_weewx_plugin-0.3.2.dist-info/entry_points.txt
aprsd_weewx_plugin-0.3.2.dist-info/pbr.json
aprsd_weewx_plugin-0.3.2.dist-info/top_level.txt
aprsd_weewx_plugin-0.3.2.dist-info/RECORD
