Metadata-Version: 2.1
Name: aprsd-weewx-plugin
Version: 0.3.2
Summary: HAM Radio APRSD that reports weather from a weewx weather station.
Author: Walter A. Boring IV
Author-email: waboring@hemna.com
License: GPL-3.0
Classifier: Topic :: Communications :: Ham Radio
Classifier: Operating System :: POSIX :: Linux
Classifier: Programming Language :: Python
Classifier: Programming Language :: Python :: 3.7
Classifier: Programming Language :: Python :: 3.8
Classifier: Programming Language :: Python :: 3.9
License-File: LICENSE
Requires-Dist: pbr
Requires-Dist: aprsd (>=3.0.0)
Requires-Dist: paho-mqtt
Requires-Dist: oslo-config
